<?xml version="1.0" encoding="UTF-8"?>

<!-- 
 ******************************************************************************
 * Copyright (c) 2011 Oracle
 * All rights reserved. This program and the accompanying materials
 * are made available under the terms of the Eclipse Public License v1.0
 * which accompanies this distribution, and is available at
 * http://www.eclipse.org/legal/epl-v10.html
 *
 * Contributors:
 *    Shenxue Zhou - initial implementation and ongoing maintenance 
 ******************************************************************************
-->

<extension xmlns="http://www.eclipse.org/sapphire/xmlns/extension">
    <action-handler>
        <action>Sapphire.Diagram.Grid.Toggle</action>
        <impl>org.eclipse.sapphire.ui.swt.graphiti.actions.ToggleDiagramGridActionHandler</impl>
        <description>Show/Hide diagram grid</description>
    </action-handler>
    <action-handler>
        <action>Sapphire.Diagram.Guides.Toggle</action>
        <impl>org.eclipse.sapphire.ui.swt.graphiti.actions.ToggleDiagramGuidesActionHandler</impl>
        <description>Show/Hide guides</description>
    </action-handler>
    <action-handler-factory>
        <action>Sapphire.Add</action>
        <impl>org.eclipse.sapphire.ui.swt.graphiti.actions.DiagramNodeAddActionHandlerFactory</impl>
        <description>Creates an add action handler for every node type.</description>
        <context>Sapphire.Diagram.Editor</context>
    </action-handler-factory>    
</extension>